JiugongQimen/Dockerfile
JiugongQimen/README.md
JiugongQimen/__init__.py
JiugongQimen/__main__.py
JiugongQimen/file.epub
JiugongQimen/index.html
JiugongQimen/css/__init__.py
JiugongQimen/css/annotations.css
JiugongQimen/css/main.css
JiugongQimen/css/normalize.css
JiugongQimen/css/popup.css
JiugongQimen/font/__init__.py
JiugongQimen/font/fontello.eot
JiugongQimen/font/fontello.svg
JiugongQimen/font/fontello.ttf
JiugongQimen/font/fontello.woff
JiugongQimen/img/__init__.py
JiugongQimen/img/annotator-glyph-sprite.png
JiugongQimen/img/annotator-icon-sprite.png
JiugongQimen/img/apple-touch-icon.png
JiugongQimen/img/cancelfullscreen.png
JiugongQimen/img/close.png
JiugongQimen/img/fullscreen.png
JiugongQimen/img/loader.gif
JiugongQimen/img/menu-icon.png
JiugongQimen/img/save.png
JiugongQimen/img/saved.png
JiugongQimen/img/settings-s.png
JiugongQimen/img/settings.png
JiugongQimen/img/star.png
JiugongQimen/js/__init__.py
JiugongQimen/js/epub.js
JiugongQimen/js/epub.min.js
JiugongQimen/js/epub.min.map
JiugongQimen/js/hooks.min.js
JiugongQimen/js/hooks.min.map
JiugongQimen/js/reader.js
JiugongQimen/js/reader.js.map
JiugongQimen/js/reader.min.js
JiugongQimen/js/reader.min.map
JiugongQimen/js/hooks/__init__.py
JiugongQimen/js/hooks/extensions/__init__.py
JiugongQimen/js/hooks/extensions/highlight.js
JiugongQimen/js/libs/__init__.py
JiugongQimen/js/libs/jquery.min.js
JiugongQimen/js/libs/localforage.min.js
JiugongQimen/js/libs/screenfull.js
JiugongQimen/js/libs/screenfull.min.js
JiugongQimen/js/libs/zip.min.js
JiugongQimen/js/plugins/__init__.py
JiugongQimen/js/plugins/hypothesis.js
JiugongQimen/js/plugins/search.js
jiugong_qimen-2022.10.6.0.dist-info/METADATA
jiugong_qimen-2022.10.6.0.dist-info/WHEEL
jiugong_qimen-2022.10.6.0.dist-info/entry_points.txt
jiugong_qimen-2022.10.6.0.dist-info/top_level.txt
jiugong_qimen-2022.10.6.0.dist-info/RECORD
